{
    "fields": [
        {
            "key": "name",
            "label": "name",
            "sortable": "true"
        },
        {
            "key": "PctAbv21MV",
            "label": "PctAbv21MV",
            "sortable": "true"
        },
        {
            "key": "PctAbv50MV",
            "label": "PctAbv50MV",
            "sortable": "true"
        },
        {
            "key": "PctAbv200MV",
            "label": "PctAbv200MV",
            "sortable": "true"
        },
        {
            "key": "NumNear52WkHigh",
            "label": "NumNear52WkHigh",
            "sortable": "true"
        },
        {
            "key": "NumNear52WkLow",
            "label": "NumNear52WkLow",
            "sortable": "true"
        },
        {
            "key": "DateUpdated",
            "label": "DateUpdated",
            "sortable": "true"
        }
    ],
    "items": [
        {
            "PctAbv21MV": 66.24,
            "PctAbv50MV": 61.51,
            "PctAbv200MV": 44.34,
            "NumNear52WkHigh": 148.0,
            "NumNear52WkLow": 101.0,
            "DateUpdated": "12-18-2023",
            "name": "Nasdaq Composite"
        },
        {
            "PctAbv21MV": 56.86,
            "PctAbv50MV": 46.04,
            "PctAbv200MV": 27.18,
            "NumNear52WkHigh": 9.0,
            "NumNear52WkLow": 31.0,
            "DateUpdated": "12-18-2023",
            "name": "Singapore "
        },
        {
            "PctAbv21MV": 36.71,
            "PctAbv50MV": 31.48,
            "PctAbv200MV": 22.63,
            "NumNear52WkHigh": 72.0,
            "NumNear52WkLow": 311.0,
            "DateUpdated": "12-18-2023",
            "name": "Hong Kong "
        },
        {
            "PctAbv21MV": 17.86,
            "PctAbv50MV": 25.34,
            "PctAbv200MV": 31.78,
            "NumNear52WkHigh": 50.0,
            "NumNear52WkLow": 984.0,
            "DateUpdated": "12-18-2023",
            "name": "China (Shenzhen + Shanghai)"
        },
        {
            "PctAbv21MV": 55.18,
            "PctAbv50MV": 52.41,
            "PctAbv200MV": 41.67,
            "NumNear52WkHigh": 68.0,
            "NumNear52WkLow": 138.0,
            "DateUpdated": "12-18-2023",
            "name": "Australia (ASX)"
        },
        {
            "PctAbv21MV": 34.07,
            "PctAbv50MV": 38.56,
            "PctAbv200MV": 51.27,
            "NumNear52WkHigh": 86.0,
            "NumNear52WkLow": 230.0,
            "DateUpdated": "12-18-2023",
            "name": "Japan (TSE)"
        },
        {
            "PctAbv21MV": 75.02,
            "PctAbv50MV": 81.12,
            "PctAbv200MV": 86.65,
            "NumNear52WkHigh": 265.0,
            "NumNear52WkLow": 12.0,
            "DateUpdated": "12-18-2023",
            "name": "India (NSE)"
        },
        {
            "PctAbv21MV": 47.79,
            "PctAbv50MV": 42.29,
            "PctAbv200MV": 45.33,
            "NumNear52WkHigh": 30.0,
            "NumNear52WkLow": 38.0,
            "DateUpdated": "12-18-2023",
            "name": "Malaysia"
        },
        {
            "PctAbv21MV": 46.04,
            "PctAbv50MV": 37.62,
            "PctAbv200MV": 29.21,
            "NumNear52WkHigh": 4.0,
            "NumNear52WkLow": 15.0,
            "DateUpdated": "12-18-2023",
            "name": "Philippines"
        },
        {
            "PctAbv21MV": 39.3,
            "PctAbv50MV": 26.28,
            "PctAbv200MV": 12.64,
            "NumNear52WkHigh": 4.0,
            "NumNear52WkLow": 66.0,
            "DateUpdated": "12-18-2023",
            "name": "Thailand"
        },
        {
            "PctAbv21MV": 70.78,
            "PctAbv50MV": 70.17,
            "PctAbv200MV": 52.11,
            "NumNear52WkHigh": 71.0,
            "NumNear52WkLow": 11.0,
            "DateUpdated": "12-18-2023",
            "name": "Korea "
        },
        {
            "PctAbv21MV": 64.47,
            "PctAbv50MV": 63.82,
            "PctAbv200MV": 43.42,
            "NumNear52WkHigh": 7.0,
            "NumNear52WkLow": 9.0,
            "DateUpdated": "12-18-2023",
            "name": "New Zealand"
        },
        {
            "PctAbv21MV": 65.17,
            "PctAbv50MV": 73.88,
            "PctAbv200MV": 69.22,
            "NumNear52WkHigh": 59.0,
            "NumNear52WkLow": 21.0,
            "DateUpdated": "12-18-2023",
            "name": "Taiwan"
        },
        {
            "PctAbv21MV": 28.21,
            "PctAbv50MV": 26.35,
            "PctAbv200MV": 25.64,
            "NumNear52WkHigh": 22.0,
            "NumNear52WkLow": 124.0,
            "DateUpdated": "12-18-2023",
            "name": "Indonesia"
        },
        {
            "PctAbv21MV": 71.17,
            "PctAbv50MV": 73.95,
            "PctAbv200MV": 56.89,
            "NumNear52WkHigh": 111.0,
            "NumNear52WkLow": 39.0,
            "DateUpdated": "12-18-2023",
            "name": "Canada (TSX)"
        },
        {
            "PctAbv21MV": 77.82,
            "PctAbv50MV": 76.17,
            "PctAbv200MV": 64.22,
            "NumNear52WkHigh": 887.0,
            "NumNear52WkLow": 184.0,
            "DateUpdated": "12-18-2023",
            "name": "United States (NYSE, Nasdaq, AMEX)"
        },
        {
            "PctAbv21MV": 77.16,
            "PctAbv50MV": 74.62,
            "PctAbv200MV": 70.41,
            "NumNear52WkHigh": 102.0,
            "NumNear52WkLow": 15.0,
            "DateUpdated": "12-18-2023",
            "name": "Brazil"
        },
        {
            "PctAbv21MV": 77.35,
            "PctAbv50MV": 70.1,
            "PctAbv200MV": 53.39,
            "NumNear52WkHigh": 74.0,
            "NumNear52WkLow": 9.0,
            "DateUpdated": "12-18-2023",
            "name": "Mexico"
        },
        {
            "PctAbv21MV": 86.44,
            "PctAbv50MV": 87.45,
            "PctAbv200MV": 73.68,
            "NumNear52WkHigh": 35.0,
            "NumNear52WkLow": 1.0,
            "DateUpdated": "12-18-2023",
            "name": "S&P 500 Index"
        },
        {
            "PctAbv21MV": 88.1,
            "PctAbv50MV": 86.51,
            "PctAbv200MV": 72.87,
            "NumNear52WkHigh": 27.0,
            "NumNear52WkLow": 0.0,
            "DateUpdated": "12-18-2023",
            "name": "S&P 400 mid-cap index"
        },
        {
            "PctAbv21MV": 89.91,
            "PctAbv50MV": 87.26,
            "PctAbv200MV": 68.03,
            "NumNear52WkHigh": 38.0,
            "NumNear52WkLow": 2.0,
            "DateUpdated": "12-18-2023",
            "name": "S&P 600 small-cap index"
        },
        {
            "PctAbv21MV": 16.21,
            "PctAbv50MV": 23.83,
            "PctAbv200MV": 32.69,
            "NumNear52WkHigh": 14.0,
            "NumNear52WkLow": 471.0,
            "DateUpdated": "12-18-2023",
            "name": "Shenzhen Stock Exchange"
        },
        {
            "PctAbv21MV": 90.0,
            "PctAbv50MV": 86.67,
            "PctAbv200MV": 80.0,
            "NumNear52WkHigh": 3.0,
            "NumNear52WkLow": 0.0,
            "DateUpdated": "12-18-2023",
            "name": "Dow Jones Industrial Average"
        },
        {
            "PctAbv21MV": 92.0,
            "PctAbv50MV": 95.0,
            "PctAbv200MV": 79.0,
            "NumNear52WkHigh": 11.0,
            "NumNear52WkLow": 1.0,
            "DateUpdated": "12-18-2023",
            "name": "Nasdaq 100 index"
        },
        {
            "PctAbv21MV": 25.56,
            "PctAbv50MV": 35.87,
            "PctAbv200MV": 60.09,
            "NumNear52WkHigh": 1.0,
            "NumNear52WkLow": 4.0,
            "DateUpdated": "12-18-2023",
            "name": "Japan Nikkei 225 index"
        },
        {
            "PctAbv21MV": 80.73,
            "PctAbv50MV": 78.12,
            "PctAbv200MV": 66.15,
            "NumNear52WkHigh": 10.0,
            "NumNear52WkLow": 3.0,
            "DateUpdated": "12-18-2023",
            "name": "Australia ASX 200 index"
        },
        {
            "PctAbv21MV": 45.57,
            "PctAbv50MV": 31.65,
            "PctAbv200MV": 20.25,
            "NumNear52WkHigh": 0.0,
            "NumNear52WkLow": 0.0,
            "DateUpdated": "12-18-2023",
            "name": "Hang Seng Index"
        },
        {
            "PctAbv21MV": 19.71,
            "PctAbv50MV": 27.05,
            "PctAbv200MV": 30.74,
            "NumNear52WkHigh": 36.0,
            "NumNear52WkLow": 513.0,
            "DateUpdated": "12-18-2023",
            "name": "Shanghai Composite Index"
        },
        {
            "PctAbv21MV": 79.31,
            "PctAbv50MV": 65.52,
            "PctAbv200MV": 58.62,
            "NumNear52WkHigh": 1.0,
            "NumNear52WkLow": 0.0,
            "DateUpdated": "12-18-2023",
            "name": "Malaysia KLSE Composite"
        },
        {
            "PctAbv21MV": 63.33,
            "PctAbv50MV": 60.0,
            "PctAbv200MV": 33.33,
            "NumNear52WkHigh": 0.0,
            "NumNear52WkLow": 0.0,
            "DateUpdated": "12-18-2023",
            "name": "Straits Times Index"
        },
        {
            "PctAbv21MV": 68.5,
            "PctAbv50MV": 68.0,
            "PctAbv200MV": 53.5,
            "NumNear52WkHigh": 4.0,
            "NumNear52WkLow": 2.0,
            "DateUpdated": "12-18-2023",
            "name": "Korea Kospi 200"
        },
        {
            "PctAbv21MV": 93.88,
            "PctAbv50MV": 97.96,
            "PctAbv200MV": 95.92,
            "NumNear52WkHigh": 11.0,
            "NumNear52WkLow": 0.0,
            "DateUpdated": "12-18-2023",
            "name": "India Nifty 50"
        },
        {
            "PctAbv21MV": 86.21,
            "PctAbv50MV": 96.55,
            "PctAbv200MV": 96.55,
            "NumNear52WkHigh": 5.0,
            "NumNear52WkLow": 0.0,
            "DateUpdated": "12-18-2023",
            "name": "India Sensex"
        }
    ]
}