{
    "fields": [
        {
            "key": "name",
            "label": "name",
            "sortable": "true"
        },
        {
            "key": "PctAbv21MV",
            "label": "PctAbv21MV",
            "sortable": "true"
        },
        {
            "key": "PctAbv50MV",
            "label": "PctAbv50MV",
            "sortable": "true"
        },
        {
            "key": "PctAbv200MV",
            "label": "PctAbv200MV",
            "sortable": "true"
        },
        {
            "key": "NumNear52WkHigh",
            "label": "NumNear52WkHigh",
            "sortable": "true"
        },
        {
            "key": "NumNear52WkLow",
            "label": "NumNear52WkLow",
            "sortable": "true"
        },
        {
            "key": "DateUpdated",
            "label": "DateUpdated",
            "sortable": "true"
        }
    ],
    "items": [
        {
            "PctAbv21MV": 49.51,
            "PctAbv50MV": 50.19,
            "PctAbv200MV": 45.77,
            "NumNear52WkHigh": 152.0,
            "NumNear52WkLow": 72.0,
            "DateUpdated": "03-07-2024",
            "name": "Nasdaq Composite"
        },
        {
            "PctAbv21MV": 41.55,
            "PctAbv50MV": 34.01,
            "PctAbv200MV": 26.32,
            "NumNear52WkHigh": 12.0,
            "NumNear52WkLow": 47.0,
            "DateUpdated": "03-07-2024",
            "name": "Singapore "
        },
        {
            "PctAbv21MV": 47.35,
            "PctAbv50MV": 40.42,
            "PctAbv200MV": 26.75,
            "NumNear52WkHigh": 90.0,
            "NumNear52WkLow": 246.0,
            "DateUpdated": "03-07-2024",
            "name": "Hong Kong "
        },
        {
            "PctAbv21MV": 64.74,
            "PctAbv50MV": 35.69,
            "PctAbv200MV": 17.11,
            "NumNear52WkHigh": 87.0,
            "NumNear52WkLow": 8.0,
            "DateUpdated": "03-07-2024",
            "name": "China (Shenzhen+Shanghai)"
        },
        {
            "PctAbv21MV": 58.03,
            "PctAbv50MV": 53.43,
            "PctAbv200MV": 45.76,
            "NumNear52WkHigh": 145.0,
            "NumNear52WkLow": 116.0,
            "DateUpdated": "03-07-2024",
            "name": "Australia (ASX)"
        },
        {
            "PctAbv21MV": 60.58,
            "PctAbv50MV": 64.07,
            "PctAbv200MV": 66.81,
            "NumNear52WkHigh": 261.0,
            "NumNear52WkLow": 87.0,
            "DateUpdated": "03-07-2024",
            "name": "Japan (TSE)"
        },
        {
            "PctAbv21MV": 32.6,
            "PctAbv50MV": 43.88,
            "PctAbv200MV": 74.64,
            "NumNear52WkHigh": 116.0,
            "NumNear52WkLow": 34.0,
            "DateUpdated": "03-07-2024",
            "name": "India (NSE)"
        },
        {
            "PctAbv21MV": 39.93,
            "PctAbv50MV": 40.24,
            "PctAbv200MV": 46.47,
            "NumNear52WkHigh": 32.0,
            "NumNear52WkLow": 69.0,
            "DateUpdated": "03-06-2024",
            "name": "Malaysia"
        },
        {
            "PctAbv21MV": 48.83,
            "PctAbv50MV": 49.74,
            "PctAbv200MV": 43.23,
            "NumNear52WkHigh": 5.0,
            "NumNear52WkLow": 13.0,
            "DateUpdated": "03-07-2024",
            "name": "Philippines"
        },
        {
            "PctAbv21MV": 33.62,
            "PctAbv50MV": 33.12,
            "PctAbv200MV": 21.25,
            "NumNear52WkHigh": 7.0,
            "NumNear52WkLow": 81.0,
            "DateUpdated": "03-07-2024",
            "name": "Thailand"
        },
        {
            "PctAbv21MV": 49.67,
            "PctAbv50MV": 52.03,
            "PctAbv200MV": 50.85,
            "NumNear52WkHigh": 63.0,
            "NumNear52WkLow": 66.0,
            "DateUpdated": "03-07-2024",
            "name": "Korea "
        },
        {
            "PctAbv21MV": 58.44,
            "PctAbv50MV": 45.7,
            "PctAbv200MV": 45.03,
            "NumNear52WkHigh": 9.0,
            "NumNear52WkLow": 11.0,
            "DateUpdated": "03-07-2024",
            "name": "New Zealand"
        },
        {
            "PctAbv21MV": 46.31,
            "PctAbv50MV": 61.82,
            "PctAbv200MV": 64.54,
            "NumNear52WkHigh": 117.0,
            "NumNear52WkLow": 51.0,
            "DateUpdated": "03-07-2024",
            "name": "Taiwan"
        },
        {
            "PctAbv21MV": 40.47,
            "PctAbv50MV": 33.19,
            "PctAbv200MV": 26.73,
            "NumNear52WkHigh": 29.0,
            "NumNear52WkLow": 89.0,
            "DateUpdated": "03-07-2024",
            "name": "Indonesia"
        },
        {
            "PctAbv21MV": 75.73,
            "PctAbv50MV": 78.6,
            "PctAbv200MV": 72.64,
            "NumNear52WkHigh": 347.0,
            "NumNear52WkLow": 18.0,
            "DateUpdated": "03-07-2024",
            "name": "Canada (TSX)"
        },
        {
            "PctAbv21MV": 69.23,
            "PctAbv50MV": 70.01,
            "PctAbv200MV": 66.83,
            "NumNear52WkHigh": 1731.0,
            "NumNear52WkLow": 137.0,
            "DateUpdated": "03-07-2024",
            "name": "United States (NYSE+Nasdaq+AMEX)"
        },
        {
            "PctAbv21MV": 59.44,
            "PctAbv50MV": 62.95,
            "PctAbv200MV": 66.99,
            "NumNear52WkHigh": 120.0,
            "NumNear52WkLow": 17.0,
            "DateUpdated": "03-07-2024",
            "name": "Brazil"
        },
        {
            "PctAbv21MV": 53.06,
            "PctAbv50MV": 55.63,
            "PctAbv200MV": 52.14,
            "NumNear52WkHigh": 47.0,
            "NumNear52WkLow": 21.0,
            "DateUpdated": "03-07-2024",
            "name": "Mexico"
        },
        {
            "PctAbv21MV": 75.15,
            "PctAbv50MV": 77.82,
            "PctAbv200MV": 75.77,
            "NumNear52WkHigh": 77.0,
            "NumNear52WkLow": 0.0,
            "DateUpdated": "03-07-2024",
            "name": "S&P 500 Index"
        },
        {
            "PctAbv21MV": 76.5,
            "PctAbv50MV": 74.04,
            "PctAbv200MV": 71.78,
            "NumNear52WkHigh": 60.0,
            "NumNear52WkLow": 1.0,
            "DateUpdated": "03-07-2024",
            "name": "S&P 400 mid-cap index"
        },
        {
            "PctAbv21MV": 61.54,
            "PctAbv50MV": 59.34,
            "PctAbv200MV": 61.03,
            "NumNear52WkHigh": 27.0,
            "NumNear52WkLow": 3.0,
            "DateUpdated": "03-07-2024",
            "name": "S&P 600 small-cap index"
        },
        {
            "PctAbv21MV": 64.76,
            "PctAbv50MV": 31.64,
            "PctAbv200MV": 14.27,
            "NumNear52WkHigh": 33.0,
            "NumNear52WkLow": 4.0,
            "DateUpdated": "03-07-2024",
            "name": "Shenzhen Stock Exchange"
        },
        {
            "PctAbv21MV": 51.72,
            "PctAbv50MV": 65.52,
            "PctAbv200MV": 72.41,
            "NumNear52WkHigh": 3.0,
            "NumNear52WkLow": 0.0,
            "DateUpdated": "03-07-2024",
            "name": "Dow Jones Industrial Average"
        },
        {
            "PctAbv21MV": 56.38,
            "PctAbv50MV": 60.64,
            "PctAbv200MV": 75.53,
            "NumNear52WkHigh": 16.0,
            "NumNear52WkLow": 0.0,
            "DateUpdated": "03-07-2024",
            "name": "Nasdaq 100 index"
        },
        {
            "PctAbv21MV": 68.61,
            "PctAbv50MV": 71.3,
            "PctAbv200MV": 79.37,
            "NumNear52WkHigh": 33.0,
            "NumNear52WkLow": 5.0,
            "DateUpdated": "03-07-2024",
            "name": "Japan Nikkei 225 index"
        },
        {
            "PctAbv21MV": 65.78,
            "PctAbv50MV": 67.38,
            "PctAbv200MV": 69.52,
            "NumNear52WkHigh": 21.0,
            "NumNear52WkLow": 2.0,
            "DateUpdated": "03-07-2024",
            "name": "Australia ASX 200 index"
        },
        {
            "PctAbv21MV": 45.57,
            "PctAbv50MV": 49.37,
            "PctAbv200MV": 30.38,
            "NumNear52WkHigh": 2.0,
            "NumNear52WkLow": 2.0,
            "DateUpdated": "03-07-2024",
            "name": "Hang Seng Index"
        },
        {
            "PctAbv21MV": 56.87,
            "PctAbv50MV": 40.31,
            "PctAbv200MV": 20.32,
            "NumNear52WkHigh": 54.0,
            "NumNear52WkLow": 4.0,
            "DateUpdated": "03-07-2024",
            "name": "Shanghai Composite Index"
        },
        {
            "PctAbv21MV": 44.83,
            "PctAbv50MV": 62.07,
            "PctAbv200MV": 62.07,
            "NumNear52WkHigh": 1.0,
            "NumNear52WkLow": 2.0,
            "DateUpdated": "03-06-2024",
            "name": "Malaysia KLSE Composite"
        },
        {
            "PctAbv21MV": 20.0,
            "PctAbv50MV": 20.0,
            "PctAbv200MV": 30.0,
            "NumNear52WkHigh": 0.0,
            "NumNear52WkLow": 2.0,
            "DateUpdated": "03-06-2024",
            "name": "Straits Times Index"
        },
        {
            "PctAbv21MV": 42.5,
            "PctAbv50MV": 47.0,
            "PctAbv200MV": 48.5,
            "NumNear52WkHigh": 7.0,
            "NumNear52WkLow": 9.0,
            "DateUpdated": "03-07-2024",
            "name": "Korea Kospi 200"
        },
        {
            "PctAbv21MV": 77.55,
            "PctAbv50MV": 67.35,
            "PctAbv200MV": 81.63,
            "NumNear52WkHigh": 7.0,
            "NumNear52WkLow": 0.0,
            "DateUpdated": "03-07-2024",
            "name": "India Nifty 50"
        },
        {
            "PctAbv21MV": 72.41,
            "PctAbv50MV": 65.52,
            "PctAbv200MV": 79.31,
            "NumNear52WkHigh": 4.0,
            "NumNear52WkLow": 0.0,
            "DateUpdated": "03-07-2024",
            "name": "India Sensex"
        }
    ]
}