{
    "fields": [
        {
            "key": "name",
            "label": "name",
            "sortable": "true"
        },
        {
            "key": "21EMA*",
            "label": "21EMA*",
            "sortable": "true"
        },
        {
            "key": "50EMA*",
            "label": "50EMA*",
            "sortable": "true"
        },
        {
            "key": "200EMA*",
            "label": "200EMA*",
            "sortable": "true"
        },
        {
            "key": "PctBelow52wkHi",
            "label": "PctBelow52wkHi",
            "sortable": "true"
        },
        {
            "key": "PctAbove52wkLo",
            "label": "PctAbove52wkLo",
            "sortable": "true"
        },
        {
            "key": "YtdGain",
            "label": "YtdGain",
            "sortable": "true"
        },
        {
            "key": "tradetime",
            "label": "tradetime",
            "sortable": "true"
        }
    ],
    "items": [
        {
            "21EMA*": -2.17,
            "50EMA*": -5.38,
            "200EMA*": 5.61,
            "PctBelow52wkHi": 24.11,
            "PctAbove52wkLo": 46.28,
            "YtdGain": -2.48,
            "tradetime": "01-13-25 00:00",
            "name": "OKB (OKB)"
        },
        {
            "21EMA*": -1.7,
            "50EMA*": -2.86,
            "200EMA*": 16.13,
            "PctBelow52wkHi": 11.08,
            "PctAbove52wkLo": 74.94,
            "YtdGain": 1.02,
            "tradetime": "01-13-25 00:00",
            "name": "Bitcoin (BTC)"
        },
        {
            "21EMA*": -5.02,
            "50EMA*": -7.96,
            "200EMA*": 4.04,
            "PctBelow52wkHi": 19.09,
            "PctAbove52wkLo": 45.74,
            "YtdGain": -2.74,
            "tradetime": "01-13-25 00:00",
            "name": "Ethereum (ETH)"
        },
        {
            "21EMA*": -5.96,
            "50EMA*": -9.81,
            "200EMA*": -0.02,
            "PctBelow52wkHi": 27.41,
            "PctAbove52wkLo": 49.3,
            "YtdGain": -1.4,
            "tradetime": "01-13-25 00:00",
            "name": "Solana (SOL)"
        },
        {
            "21EMA*": -1.34,
            "50EMA*": -0.91,
            "200EMA*": 10.07,
            "PctBelow52wkHi": 7.9,
            "PctAbove52wkLo": 48.72,
            "YtdGain": -1.42,
            "tradetime": "01-13-25 00:00",
            "name": "Binance Coin (BNB)"
        },
        {
            "21EMA*": 1.96,
            "50EMA*": 3.47,
            "200EMA*": 75.24,
            "PctBelow52wkHi": 13.43,
            "PctAbove52wkLo": 459.62,
            "YtdGain": 12.94,
            "tradetime": "01-13-25 00:00",
            "name": "Ripple (XRP)"
        },
        {
            "21EMA*": -5.98,
            "50EMA*": -12.28,
            "200EMA*": 6.55,
            "PctBelow52wkHi": 32.34,
            "PctAbove52wkLo": 86.65,
            "YtdGain": 2.24,
            "tradetime": "01-13-25 00:00",
            "name": "Avalanche (AVAX)"
        },
        {
            "21EMA*": -5.52,
            "50EMA*": -12.99,
            "200EMA*": 7.75,
            "PctBelow52wkHi": 37.42,
            "PctAbove52wkLo": 78.78,
            "YtdGain": 0.97,
            "tradetime": "01-13-25 00:00",
            "name": "Polkadot (DOT)"
        },
        {
            "21EMA*": -2.87,
            "50EMA*": -7.69,
            "200EMA*": 29.71,
            "PctBelow52wkHi": 28.7,
            "PctAbove52wkLo": 260.22,
            "YtdGain": 5.54,
            "tradetime": "01-13-25 00:00",
            "name": "Dogecoin (DOGE)"
        },
        {
            "21EMA*": -5.26,
            "50EMA*": -12.65,
            "200EMA*": -2.74,
            "PctBelow52wkHi": 39.18,
            "PctAbove52wkLo": 56.52,
            "YtdGain": 1.31,
            "tradetime": "01-13-25 00:00",
            "name": "Matic (MATIC)"
        },
        {
            "21EMA*": -6.72,
            "50EMA*": -22.15,
            "200EMA*": -6.75,
            "PctBelow52wkHi": 49.37,
            "PctAbove52wkLo": 147.56,
            "YtdGain": 6.66,
            "tradetime": "01-13-25 00:00",
            "name": "Fantom (FTM)"
        },
        {
            "21EMA*": -1.74,
            "50EMA*": -4.65,
            "200EMA*": 17.66,
            "PctBelow52wkHi": 23.96,
            "PctAbove52wkLo": 85.04,
            "YtdGain": 0.51,
            "tradetime": "01-13-25 00:00",
            "name": "Litecoin (LTC)"
        },
        {
            "21EMA*": -1.33,
            "50EMA*": -7.15,
            "200EMA*": 5.22,
            "PctBelow52wkHi": 28.65,
            "PctAbove52wkLo": 50.83,
            "YtdGain": 2.52,
            "tradetime": "01-13-25 00:00",
            "name": "Bitcoin Cash (BCH)"
        },
        {
            "21EMA*": -2.17,
            "50EMA*": -10.7,
            "200EMA*": 6.37,
            "PctBelow52wkHi": 36.58,
            "PctAbove52wkLo": 80.25,
            "YtdGain": 6.84,
            "tradetime": "01-13-25 00:00",
            "name": "Cosmos (ATOM)"
        },
        {
            "21EMA*": -5.7,
            "50EMA*": -12.95,
            "200EMA*": 9.84,
            "PctBelow52wkHi": 34.06,
            "PctAbove52wkLo": 100.99,
            "YtdGain": 0.5,
            "tradetime": "01-13-25 00:00",
            "name": "Crypto.com Coin (CRO)"
        },
        {
            "21EMA*": -5.39,
            "50EMA*": -12.82,
            "200EMA*": -5.15,
            "PctBelow52wkHi": 38.88,
            "PctAbove52wkLo": 43.45,
            "YtdGain": 3.25,
            "tradetime": "01-13-25 00:00",
            "name": "Near Protocol (NEAR)"
        },
        {
            "21EMA*": -8.14,
            "50EMA*": -11.81,
            "200EMA*": 18.74,
            "PctBelow52wkHi": 31.65,
            "PctAbove52wkLo": 111.02,
            "YtdGain": 0.07,
            "tradetime": "01-13-25 00:00",
            "name": "Chainlink (LINK)"
        },
        {
            "21EMA*": 2.32,
            "50EMA*": 2.04,
            "200EMA*": 24.46,
            "PctBelow52wkHi": 2.29,
            "PctAbove52wkLo": 73.05,
            "YtdGain": 3.21,
            "tradetime": "01-13-25 00:00",
            "name": "Bitfinex Unus Sed (LEO)"
        },
        {
            "21EMA*": -11.96,
            "50EMA*": -9.96,
            "200EMA*": 32.25,
            "PctBelow52wkHi": 26.5,
            "PctAbove52wkLo": 260.85,
            "YtdGain": -8.54,
            "tradetime": "01-13-25 00:00",
            "name": "Aave (AAVE)"
        },
        {
            "21EMA*": -4.51,
            "50EMA*": -6.37,
            "200EMA*": 19.67,
            "PctBelow52wkHi": 42.77,
            "PctAbove52wkLo": 119.44,
            "YtdGain": -4.09,
            "tradetime": "01-13-25 00:00",
            "name": "Tron (TRX)"
        },
        {
            "21EMA*": -2.78,
            "50EMA*": -6.96,
            "200EMA*": -6.78,
            "PctBelow52wkHi": 34.2,
            "PctAbove52wkLo": 16.37,
            "YtdGain": -2.0,
            "tradetime": "01-13-25 00:00",
            "name": "Toncoin (TON)"
        },
        {
            "21EMA*": -1.62,
            "50EMA*": -7.33,
            "200EMA*": 31.46,
            "PctBelow52wkHi": 36.63,
            "PctAbove52wkLo": 160.27,
            "YtdGain": 8.53,
            "tradetime": "01-13-25 00:00",
            "name": "Sandbox (SAND)"
        },
        {
            "21EMA*": -3.72,
            "50EMA*": -9.75,
            "200EMA*": 4.17,
            "PctBelow52wkHi": 34.05,
            "PctAbove52wkLo": 50.09,
            "YtdGain": 1.62,
            "tradetime": "01-13-25 00:00",
            "name": "Axie Infinity (AXS)"
        },
        {
            "21EMA*": -0.33,
            "50EMA*": -3.38,
            "200EMA*": 48.02,
            "PctBelow52wkHi": 27.51,
            "PctAbove52wkLo": 238.79,
            "YtdGain": 10.97,
            "tradetime": "01-13-25 00:00",
            "name": "Algorand (ALGO)"
        },
        {
            "21EMA*": -3.72,
            "50EMA*": -6.81,
            "200EMA*": 35.16,
            "PctBelow52wkHi": 24.96,
            "PctAbove52wkLo": 194.96,
            "YtdGain": 9.48,
            "tradetime": "01-13-25 00:00",
            "name": "Cardano (ADA)"
        }
    ]
}