{
    "fields": [
        {
            "key": "name",
            "label": "name",
            "sortable": "true"
        },
        {
            "key": "21EMA*",
            "label": "21EMA*",
            "sortable": "true"
        },
        {
            "key": "50EMA*",
            "label": "50EMA*",
            "sortable": "true"
        },
        {
            "key": "200EMA*",
            "label": "200EMA*",
            "sortable": "true"
        },
        {
            "key": "PctBelow52wkHi",
            "label": "PctBelow52wkHi",
            "sortable": "true"
        },
        {
            "key": "PctAbove52wkLo",
            "label": "PctAbove52wkLo",
            "sortable": "true"
        },
        {
            "key": "YtdGain",
            "label": "YtdGain",
            "sortable": "true"
        },
        {
            "key": "tradetime",
            "label": "tradetime",
            "sortable": "true"
        }
    ],
    "items": [
        {
            "21EMA*": 10.56,
            "50EMA*": 11.86,
            "200EMA*": 16.14,
            "PctBelow52wkHi": 5.89,
            "PctAbove52wkLo": 42.3,
            "YtdGain": 6.89,
            "tradetime": "03-07-24 00:00",
            "name": "OKB (OKB)"
        },
        {
            "21EMA*": 15.8,
            "50EMA*": 29.11,
            "200EMA*": 63.38,
            "PctBelow52wkHi": 2.03,
            "PctAbove52wkLo": 166.04,
            "YtdGain": 58.31,
            "tradetime": "03-07-24 00:00",
            "name": "Bitcoin (BTC)"
        },
        {
            "21EMA*": 19.97,
            "50EMA*": 34.53,
            "200EMA*": 67.93,
            "PctBelow52wkHi": -1.0,
            "PctAbove52wkLo": 150.97,
            "YtdGain": 69.31,
            "tradetime": "03-07-24 00:00",
            "name": "Ethereum (ETH)"
        },
        {
            "21EMA*": 22.32,
            "50EMA*": 33.36,
            "200EMA*": 94.4,
            "PctBelow52wkHi": -8.35,
            "PctAbove52wkLo": 802.71,
            "YtdGain": 41.93,
            "tradetime": "03-07-24 00:00",
            "name": "Solana (SOL)"
        },
        {
            "21EMA*": 22.39,
            "50EMA*": 34.09,
            "200EMA*": 61.98,
            "PctBelow52wkHi": -10.74,
            "PctAbove52wkLo": 130.86,
            "YtdGain": 51.96,
            "tradetime": "03-07-24 00:00",
            "name": "Binance Coin (BNB)"
        },
        {
            "21EMA*": 7.93,
            "50EMA*": 10.78,
            "200EMA*": 11.54,
            "PctBelow52wkHi": 23.42,
            "PctAbove52wkLo": 35.54,
            "YtdGain": 2.14,
            "tradetime": "03-07-24 00:00",
            "name": "Ripple (XRP)"
        },
        {
            "21EMA*": 8.16,
            "50EMA*": 13.7,
            "200EMA*": 52.07,
            "PctBelow52wkHi": 10.3,
            "PctAbove52wkLo": 393.45,
            "YtdGain": 12.46,
            "tradetime": "03-07-24 00:00",
            "name": "Avalanche (AVAX)"
        },
        {
            "21EMA*": 21.51,
            "50EMA*": 32.1,
            "200EMA*": 58.53,
            "PctBelow52wkHi": -0.06,
            "PctAbove52wkLo": 185.72,
            "YtdGain": 27.14,
            "tradetime": "03-07-24 00:00",
            "name": "Polkadot (DOT)"
        },
        {
            "21EMA*": 32.18,
            "50EMA*": 55.96,
            "200EMA*": 87.09,
            "PctBelow52wkHi": 13.65,
            "PctAbove52wkLo": 172.78,
            "YtdGain": 77.26,
            "tradetime": "03-07-24 00:00",
            "name": "Dogecoin (DOGE)"
        },
        {
            "21EMA*": 14.45,
            "50EMA*": 23.44,
            "200EMA*": 40.2,
            "PctBelow52wkHi": -1.06,
            "PctAbove52wkLo": 130.32,
            "YtdGain": 19.4,
            "tradetime": "03-07-24 00:00",
            "name": "Matic (MATIC)"
        },
        {
            "21EMA*": 61.74,
            "50EMA*": 83.67,
            "200EMA*": 125.38,
            "PctBelow52wkHi": -16.71,
            "PctAbove52wkLo": 369.69,
            "YtdGain": 74.46,
            "tradetime": "03-07-24 00:00",
            "name": "Fantom (FTM)"
        },
        {
            "21EMA*": 12.47,
            "50EMA*": 19.03,
            "200EMA*": 21.01,
            "PctBelow52wkHi": 22.06,
            "PctAbove52wkLo": 49.97,
            "YtdGain": 21.15,
            "tradetime": "03-07-24 00:00",
            "name": "Litecoin (LTC)"
        },
        {
            "21EMA*": 26.85,
            "50EMA*": 46.09,
            "200EMA*": 76.37,
            "PctBelow52wkHi": 13.72,
            "PctAbove52wkLo": 304.91,
            "YtdGain": 66.51,
            "tradetime": "03-07-24 00:00",
            "name": "Bitcoin Cash (BCH)"
        },
        {
            "21EMA*": 22.71,
            "50EMA*": 30.91,
            "200EMA*": 42.81,
            "PctBelow52wkHi": 1.23,
            "PctAbove52wkLo": 122.42,
            "YtdGain": 31.44,
            "tradetime": "03-07-24 00:00",
            "name": "Cosmos (ATOM)"
        },
        {
            "21EMA*": 35.14,
            "50EMA*": 54.14,
            "200EMA*": 84.65,
            "PctBelow52wkHi": -0.49,
            "PctAbove52wkLo": 221.98,
            "YtdGain": 59.52,
            "tradetime": "03-07-24 00:00",
            "name": "Crypto.com Coin (CRO)"
        },
        {
            "21EMA*": 38.22,
            "50EMA*": 55.61,
            "200EMA*": 110.32,
            "PctBelow52wkHi": 4.62,
            "PctAbove52wkLo": 459.64,
            "YtdGain": 51.35,
            "tradetime": "03-07-24 00:00",
            "name": "Near Protocol (NEAR)"
        },
        {
            "21EMA*": 3.65,
            "50EMA*": 10.42,
            "200EMA*": 43.88,
            "PctBelow52wkHi": 6.03,
            "PctAbove52wkLo": 293.21,
            "YtdGain": 34.77,
            "tradetime": "03-07-24 00:00",
            "name": "Chainlink (LINK)"
        },
        {
            "21EMA*": 19.27,
            "50EMA*": 26.75,
            "200EMA*": 36.04,
            "PctBelow52wkHi": 0.53,
            "PctAbove52wkLo": 55.14,
            "YtdGain": 38.45,
            "tradetime": "03-07-24 00:00",
            "name": "Bitfinex Unus Sed (LEO)"
        },
        {
            "21EMA*": 27.17,
            "50EMA*": 34.1,
            "200EMA*": 48.98,
            "PctBelow52wkHi": -4.4,
            "PctAbove52wkLo": 161.7,
            "YtdGain": 22.77,
            "tradetime": "03-07-24 00:00",
            "name": "Aave (AAVE)"
        },
        {
            "21EMA*": 0.57,
            "50EMA*": 7.22,
            "200EMA*": 29.24,
            "PctBelow52wkHi": 3.9,
            "PctAbove52wkLo": 96.18,
            "YtdGain": 27.4,
            "tradetime": "03-07-24 00:00",
            "name": "Tron (TRX)"
        },
        {
            "21EMA*": 14.31,
            "50EMA*": 20.5,
            "200EMA*": 28.91,
            "PctBelow52wkHi": -0.79,
            "PctAbove52wkLo": 133.05,
            "YtdGain": 18.63,
            "tradetime": "03-07-24 00:00",
            "name": "Toncoin (TON)"
        },
        {
            "21EMA*": 19.81,
            "50EMA*": 31.03,
            "200EMA*": 46.08,
            "PctBelow52wkHi": -1.17,
            "PctAbove52wkLo": 148.81,
            "YtdGain": 17.43,
            "tradetime": "03-07-24 00:00",
            "name": "Sandbox (SAND)"
        },
        {
            "21EMA*": 17.6,
            "50EMA*": 27.8,
            "200EMA*": 46.53,
            "PctBelow52wkHi": -0.15,
            "PctAbove52wkLo": 159.76,
            "YtdGain": 21.03,
            "tradetime": "03-07-24 00:00",
            "name": "Axie Infinity (AXS)"
        },
        {
            "21EMA*": 30.45,
            "50EMA*": 41.87,
            "200EMA*": 65.54,
            "PctBelow52wkHi": -11.39,
            "PctAbove52wkLo": 218.82,
            "YtdGain": 26.59,
            "tradetime": "03-07-24 00:00",
            "name": "Algorand (ALGO)"
        },
        {
            "21EMA*": 14.07,
            "50EMA*": 24.65,
            "200EMA*": 57.05,
            "PctBelow52wkHi": 3.31,
            "PctAbove52wkLo": 208.29,
            "YtdGain": 23.89,
            "tradetime": "03-07-24 00:00",
            "name": "Cardano (ADA)"
        }
    ]
}