{
    "fields": [
        {
            "key": "name",
            "label": "name",
            "sortable": "true"
        },
        {
            "key": "21EMA*",
            "label": "21EMA*",
            "sortable": "true"
        },
        {
            "key": "50EMA*",
            "label": "50EMA*",
            "sortable": "true"
        },
        {
            "key": "200EMA*",
            "label": "200EMA*",
            "sortable": "true"
        },
        {
            "key": "PctBelow52wkHi",
            "label": "PctBelow52wkHi",
            "sortable": "true"
        },
        {
            "key": "PctAbove52wkLo",
            "label": "PctAbove52wkLo",
            "sortable": "true"
        },
        {
            "key": "YtdGain",
            "label": "YtdGain",
            "sortable": "true"
        },
        {
            "key": "tradetime",
            "label": "tradetime",
            "sortable": "true"
        }
    ],
    "items": [
        {
            "21EMA*": 1.07,
            "50EMA*": 11.81,
            "200EMA*": 22.31,
            "PctBelow52wkHi": 18.03,
            "PctAbove52wkLo": 67.02,
            "YtdGain": -0.29,
            "tradetime": "12-10-24 00:00",
            "name": "OKB (OKB)"
        },
        {
            "21EMA*": 2.2,
            "50EMA*": 11.91,
            "200EMA*": 37.73,
            "PctBelow52wkHi": 3.73,
            "PctAbove52wkLo": 80.66,
            "YtdGain": 130.49,
            "tradetime": "12-10-24 00:00",
            "name": "Bitcoin (BTC)"
        },
        {
            "21EMA*": 3.01,
            "50EMA*": 13.84,
            "200EMA*": 25.97,
            "PctBelow52wkHi": 7.19,
            "PctAbove52wkLo": 67.18,
            "YtdGain": 62.91,
            "tradetime": "12-10-24 00:00",
            "name": "Ethereum (ETH)"
        },
        {
            "21EMA*": -5.32,
            "50EMA*": 2.72,
            "200EMA*": 28.5,
            "PctBelow52wkHi": 14.93,
            "PctAbove52wkLo": 74.97,
            "YtdGain": 115.08,
            "tradetime": "12-10-24 00:00",
            "name": "Solana (SOL)"
        },
        {
            "21EMA*": 1.22,
            "50EMA*": 7.22,
            "200EMA*": 19.51,
            "PctBelow52wkHi": 8.29,
            "PctAbove52wkLo": 48.1,
            "YtdGain": 120.69,
            "tradetime": "12-10-24 00:00",
            "name": "Binance Coin (BNB)"
        },
        {
            "21EMA*": 14.35,
            "50EMA*": 58.09,
            "200EMA*": 169.54,
            "PctBelow52wkHi": 17.88,
            "PctAbove52wkLo": 430.85,
            "YtdGain": 262.15,
            "tradetime": "12-10-24 00:00",
            "name": "Ripple (XRP)"
        },
        {
            "21EMA*": -0.23,
            "50EMA*": 17.24,
            "200EMA*": 43.11,
            "PctBelow52wkHi": 21.59,
            "PctAbove52wkLo": 131.91,
            "YtdGain": 17.58,
            "tradetime": "12-10-24 00:00",
            "name": "Avalanche (AVAX)"
        },
        {
            "21EMA*": -2.69,
            "50EMA*": 19.95,
            "200EMA*": 44.84,
            "PctBelow52wkHi": 20.26,
            "PctAbove52wkLo": 127.8,
            "YtdGain": 4.1,
            "tradetime": "12-10-24 00:00",
            "name": "Polkadot (DOT)"
        },
        {
            "21EMA*": 2.16,
            "50EMA*": 25.79,
            "200EMA*": 109.8,
            "PctBelow52wkHi": 11.15,
            "PctAbove52wkLo": 348.86,
            "YtdGain": 365.99,
            "tradetime": "12-10-24 00:00",
            "name": "Dogecoin (DOGE)"
        },
        {
            "21EMA*": -2.1,
            "50EMA*": 14.87,
            "200EMA*": 14.46,
            "PctBelow52wkHi": 44.19,
            "PctAbove52wkLo": 100.17,
            "YtdGain": -39.89,
            "tradetime": "12-10-24 00:00",
            "name": "Matic (MATIC)"
        },
        {
            "21EMA*": 3.31,
            "50EMA*": 23.06,
            "200EMA*": 63.88,
            "PctBelow52wkHi": 15.47,
            "PctAbove52wkLo": 285.13,
            "YtdGain": 138.01,
            "tradetime": "12-10-24 00:00",
            "name": "Fantom (FTM)"
        },
        {
            "21EMA*": -1.95,
            "50EMA*": 15.13,
            "200EMA*": 40.02,
            "PctBelow52wkHi": 18.72,
            "PctAbove52wkLo": 97.81,
            "YtdGain": 52.04,
            "tradetime": "12-10-24 00:00",
            "name": "Litecoin (LTC)"
        },
        {
            "21EMA*": 2.81,
            "50EMA*": 16.81,
            "200EMA*": 38.23,
            "PctBelow52wkHi": 20.53,
            "PctAbove52wkLo": 87.37,
            "YtdGain": 112.9,
            "tradetime": "12-10-24 00:00",
            "name": "Bitcoin Cash (BCH)"
        },
        {
            "21EMA*": -1.55,
            "50EMA*": 18.85,
            "200EMA*": 31.86,
            "PctBelow52wkHi": 33.31,
            "PctAbove52wkLo": 129.94,
            "YtdGain": -20.5,
            "tradetime": "12-10-24 00:00",
            "name": "Cosmos (ATOM)"
        },
        {
            "21EMA*": -5.68,
            "50EMA*": 12.54,
            "200EMA*": 52.94,
            "PctBelow52wkHi": 18.94,
            "PctAbove52wkLo": 147.09,
            "YtdGain": 76.14,
            "tradetime": "12-10-24 00:00",
            "name": "Crypto.com Coin (CRO)"
        },
        {
            "21EMA*": -4.34,
            "50EMA*": 8.75,
            "200EMA*": 25.65,
            "PctBelow52wkHi": 20.67,
            "PctAbove52wkLo": 86.16,
            "YtdGain": 80.07,
            "tradetime": "12-10-24 00:00",
            "name": "Near Protocol (NEAR)"
        },
        {
            "21EMA*": 8.4,
            "50EMA*": 30.74,
            "200EMA*": 59.05,
            "PctBelow52wkHi": 14.27,
            "PctAbove52wkLo": 136.29,
            "YtdGain": 50.06,
            "tradetime": "12-10-24 00:00",
            "name": "Chainlink (LINK)"
        },
        {
            "21EMA*": 8.5,
            "50EMA*": 20.92,
            "200EMA*": 47.1,
            "PctBelow52wkHi": 0.96,
            "PctAbove52wkLo": 75.41,
            "YtdGain": 139.6,
            "tradetime": "12-10-24 00:00",
            "name": "Bitfinex Unus Sed (LEO)"
        },
        {
            "21EMA*": 14.45,
            "50EMA*": 32.91,
            "200EMA*": 77.13,
            "PctBelow52wkHi": 8.38,
            "PctAbove52wkLo": 230.97,
            "YtdGain": 138.42,
            "tradetime": "12-10-24 00:00",
            "name": "Aave (AAVE)"
        },
        {
            "21EMA*": 1.73,
            "50EMA*": 20.51,
            "200EMA*": 59.22,
            "PctBelow52wkHi": 38.29,
            "PctAbove52wkLo": 140.53,
            "YtdGain": 143.9,
            "tradetime": "12-10-24 00:00",
            "name": "Tron (TRX)"
        },
        {
            "21EMA*": -7.93,
            "50EMA*": -1.54,
            "200EMA*": 3.21,
            "PctBelow52wkHi": 28.88,
            "PctAbove52wkLo": 25.79,
            "YtdGain": 149.97,
            "tradetime": "12-10-24 00:00",
            "name": "Toncoin (TON)"
        },
        {
            "21EMA*": 7.26,
            "50EMA*": 42.42,
            "200EMA*": 91.27,
            "PctBelow52wkHi": 20.44,
            "PctAbove52wkLo": 226.79,
            "YtdGain": 24.67,
            "tradetime": "12-10-24 00:00",
            "name": "Sandbox (SAND)"
        },
        {
            "21EMA*": -4.68,
            "50EMA*": 12.01,
            "200EMA*": 25.87,
            "PctBelow52wkHi": 32.73,
            "PctAbove52wkLo": 82.67,
            "YtdGain": -13.38,
            "tradetime": "12-10-24 00:00",
            "name": "Axie Infinity (AXS)"
        },
        {
            "21EMA*": 8.08,
            "50EMA*": 46.89,
            "200EMA*": 122.24,
            "PctBelow52wkHi": 17.56,
            "PctAbove52wkLo": 285.27,
            "YtdGain": 88.92,
            "tradetime": "12-10-24 00:00",
            "name": "Algorand (ALGO)"
        },
        {
            "21EMA*": -2.14,
            "50EMA*": 24.99,
            "200EMA*": 87.93,
            "PctBelow52wkHi": 17.97,
            "PctAbove52wkLo": 222.45,
            "YtdGain": 67.77,
            "tradetime": "12-10-24 00:00",
            "name": "Cardano (ADA)"
        }
    ]
}