{
    "fields": [
        {
            "key": "name",
            "label": "name",
            "sortable": "true"
        },
        {
            "key": "21EMA*",
            "label": "21EMA*",
            "sortable": "true"
        },
        {
            "key": "50EMA*",
            "label": "50EMA*",
            "sortable": "true"
        },
        {
            "key": "200EMA*",
            "label": "200EMA*",
            "sortable": "true"
        },
        {
            "key": "PctBelow52wkHi",
            "label": "PctBelow52wkHi",
            "sortable": "true"
        },
        {
            "key": "PctAbove52wkLo",
            "label": "PctAbove52wkLo",
            "sortable": "true"
        },
        {
            "key": "Year gain (%)",
            "label": "Year gain (%)",
            "sortable": "true"
        },
        {
            "key": "FxGain",
            "label": "FxGain",
            "sortable": "true"
        },
        {
            "key": "Year gain USD-adj (%)",
            "label": "Year gain USD-adj (%)",
            "sortable": "true"
        },
        {
            "key": "tradetime",
            "label": "tradetime",
            "sortable": "true"
        }
    ],
    "items": [
        {
            "21EMA*": 2.83,
            "50EMA*": 3.1,
            "200EMA*": 6.15,
            "PctBelow52wkHi": -0.57,
            "PctAbove52wkLo": 21.01,
            "Year gain (%)": 8.18,
            "FxGain": -2.07,
            "Year gain USD-adj (%)": 5.95,
            "tradetime": "07-12-24 00:00",
            "name": "Canada TSX Composite"
        },
        {
            "21EMA*": 1.95,
            "50EMA*": 1.95,
            "200EMA*": 3.47,
            "PctBelow52wkHi": 8.89,
            "PctAbove52wkLo": 22.27,
            "Year gain (%)": 7.31,
            "FxGain": 0.02,
            "Year gain USD-adj (%)": 7.33,
            "tradetime": "07-12-24 00:00",
            "name": "HongKong Hang Seng"
        },
        {
            "21EMA*": 3.19,
            "50EMA*": 4.76,
            "200EMA*": 7.69,
            "PctBelow52wkHi": -0.0,
            "PctAbove52wkLo": 14.56,
            "Year gain (%)": 7.95,
            "FxGain": -1.62,
            "Year gain USD-adj (%)": 6.2,
            "tradetime": "07-12-24 00:00",
            "name": "Singapore Straits Times"
        },
        {
            "21EMA*": -0.18,
            "50EMA*": -1.26,
            "200EMA*": -2.79,
            "PctBelow52wkHi": 13.63,
            "PctAbove52wkLo": 9.21,
            "Year gain (%)": 1.2,
            "FxGain": -2.1,
            "Year gain USD-adj (%)": -0.92,
            "tradetime": "07-12-24 00:00",
            "name": "China CSI 300"
        },
        {
            "21EMA*": -0.39,
            "50EMA*": -1.51,
            "200EMA*": -2.42,
            "PctBelow52wkHi": 9.72,
            "PctAbove52wkLo": 9.96,
            "Year gain (%)": -0.12,
            "FxGain": -2.1,
            "Year gain USD-adj (%)": -2.22,
            "tradetime": "07-12-24 00:00",
            "name": "Shanghai Composite"
        },
        {
            "21EMA*": -0.62,
            "50EMA*": -3.14,
            "200EMA*": -8.77,
            "PctBelow52wkHi": 22.36,
            "PctAbove52wkLo": 12.87,
            "Year gain (%)": -11.99,
            "FxGain": -2.1,
            "Year gain USD-adj (%)": -13.84,
            "tradetime": "07-12-24 00:00",
            "name": "Shenzhen Composite "
        },
        {
            "21EMA*": 1.99,
            "50EMA*": 2.43,
            "200EMA*": 5.06,
            "PctBelow52wkHi": -0.0,
            "PctAbove52wkLo": 17.52,
            "Year gain (%)": 4.85,
            "FxGain": -0.4,
            "Year gain USD-adj (%)": 4.43,
            "tradetime": "07-12-24 00:00",
            "name": "Australia ASX200"
        },
        {
            "21EMA*": 2.26,
            "50EMA*": 4.29,
            "200EMA*": 11.83,
            "PctBelow52wkHi": 2.45,
            "PctAbove52wkLo": 34.93,
            "Year gain (%)": 23.09,
            "FxGain": -10.67,
            "Year gain USD-adj (%)": 9.95,
            "tradetime": "07-12-24 00:00",
            "name": "Japan Nikkei 225"
        },
        {
            "21EMA*": 2.66,
            "50EMA*": 6.03,
            "200EMA*": 16.42,
            "PctBelow52wkHi": 1.66,
            "PctAbove52wkLo": 44.1,
            "Year gain (%)": 20.83,
            "FxGain": 0.0,
            "Year gain USD-adj (%)": 20.83,
            "tradetime": "07-12-24 00:00",
            "name": "Nasdaq 100"
        },
        {
            "21EMA*": 2.23,
            "50EMA*": 4.39,
            "200EMA*": 12.41,
            "PctBelow52wkHi": 0.33,
            "PctAbove52wkLo": 36.38,
            "Year gain (%)": 17.73,
            "FxGain": 0.0,
            "Year gain USD-adj (%)": 17.73,
            "tradetime": "07-12-24 00:00",
            "name": "S&P 500"
        },
        {
            "21EMA*": 1.99,
            "50EMA*": 2.49,
            "200EMA*": 6.23,
            "PctBelow52wkHi": 0.01,
            "PctAbove52wkLo": 23.39,
            "Year gain (%)": 6.13,
            "FxGain": 0.0,
            "Year gain USD-adj (%)": 6.13,
            "tradetime": "07-12-24 00:00",
            "name": "Dow Jones Industrial"
        },
        {
            "21EMA*": 3.2,
            "50EMA*": 3.08,
            "200EMA*": 7.21,
            "PctBelow52wkHi": 0.84,
            "PctAbove52wkLo": 29.82,
            "Year gain (%)": 8.6,
            "FxGain": 0.0,
            "Year gain USD-adj (%)": 8.6,
            "tradetime": "07-12-24 00:00",
            "name": "S&P 400 mid-cap"
        },
        {
            "21EMA*": 4.25,
            "50EMA*": 4.07,
            "200EMA*": 6.38,
            "PctBelow52wkHi": -0.35,
            "PctAbove52wkLo": 26.35,
            "Year gain (%)": 2.44,
            "FxGain": 0.0,
            "Year gain USD-adj (%)": 2.44,
            "tradetime": "07-12-24 00:00",
            "name": "S&P 600 small-cap"
        },
        {
            "21EMA*": 1.96,
            "50EMA*": 2.28,
            "200EMA*": 7.54,
            "PctBelow52wkHi": 0.64,
            "PctAbove52wkLo": 27.65,
            "Year gain (%)": 11.92,
            "FxGain": -1.18,
            "Year gain USD-adj (%)": 10.6,
            "tradetime": "07-12-24 00:00",
            "name": "German DAX"
        },
        {
            "21EMA*": 1.08,
            "50EMA*": 1.12,
            "200EMA*": 6.81,
            "PctBelow52wkHi": 6.26,
            "PctAbove52wkLo": 13.67,
            "Year gain (%)": 2.4,
            "FxGain": -1.18,
            "Year gain USD-adj (%)": 1.19,
            "tradetime": "07-12-24 00:00",
            "name": "Italy MIB index"
        },
        {
            "21EMA*": 0.56,
            "50EMA*": 0.86,
            "200EMA*": 4.41,
            "PctBelow52wkHi": 2.28,
            "PctAbove52wkLo": 13.73,
            "Year gain (%)": 6.72,
            "FxGain": 2.03,
            "Year gain USD-adj (%)": 8.88,
            "tradetime": "07-12-24 00:00",
            "name": "UK FTSE 100"
        },
        {
            "21EMA*": 1.69,
            "50EMA*": 1.64,
            "200EMA*": 6.13,
            "PctBelow52wkHi": 1.13,
            "PctAbove52wkLo": 25.62,
            "Year gain (%)": 11.53,
            "FxGain": -1.18,
            "Year gain USD-adj (%)": 10.22,
            "tradetime": "07-12-24 00:00",
            "name": "EURO STOXX 50"
        },
        {
            "21EMA*": 2.14,
            "50EMA*": 4.58,
            "200EMA*": 11.47,
            "PctBelow52wkHi": 0.0,
            "PctAbove52wkLo": 27.87,
            "Year gain (%)": 11.46,
            "FxGain": -0.39,
            "Year gain USD-adj (%)": 11.03,
            "tradetime": "07-12-24 00:00",
            "name": "India BSE SENSEX"
        },
        {
            "21EMA*": 0.72,
            "50EMA*": 1.35,
            "200EMA*": 5.32,
            "PctBelow52wkHi": 0.62,
            "PctAbove52wkLo": 17.61,
            "Year gain (%)": 11.3,
            "FxGain": -1.76,
            "Year gain USD-adj (%)": 9.34,
            "tradetime": "07-12-24 00:00",
            "name": "Malaysia KLSE Composite "
        },
        {
            "21EMA*": 0.81,
            "50EMA*": -0.73,
            "200EMA*": 0.45,
            "PctBelow52wkHi": 6.26,
            "PctAbove52wkLo": 13.67,
            "Year gain (%)": 2.4,
            "FxGain": -1.18,
            "Year gain USD-adj (%)": 1.19,
            "tradetime": "07-12-24 00:00",
            "name": "French CAC 40"
        },
        {
            "21EMA*": 2.07,
            "50EMA*": 1.66,
            "200EMA*": 0.99,
            "PctBelow52wkHi": 5.31,
            "PctAbove52wkLo": 10.86,
            "Year gain (%)": 2.47,
            "FxGain": -5.16,
            "Year gain USD-adj (%)": -2.82,
            "tradetime": "07-11-24 00:00",
            "name": "Philippine stock exchange index"
        },
        {
            "21EMA*": 1.1,
            "50EMA*": 0.05,
            "200EMA*": -4.31,
            "PctBelow52wkHi": 15.52,
            "PctAbove52wkLo": 3.37,
            "Year gain (%)": -5.92,
            "FxGain": -4.69,
            "Year gain USD-adj (%)": -10.33,
            "tradetime": "07-12-24 00:00",
            "name": "Thailand SET"
        },
        {
            "21EMA*": 1.6,
            "50EMA*": 3.8,
            "200EMA*": 9.53,
            "PctBelow52wkHi": 1.56,
            "PctAbove52wkLo": 28.38,
            "Year gain (%)": 9.58,
            "FxGain": -5.78,
            "Year gain USD-adj (%)": 3.25,
            "tradetime": "07-12-24 00:00",
            "name": "Korea KOSPI 200"
        },
        {
            "21EMA*": 0.65,
            "50EMA*": -0.23,
            "200EMA*": -1.42,
            "PctBelow52wkHi": 12.15,
            "PctAbove52wkLo": 11.83,
            "Year gain (%)": 2.91,
            "FxGain": -2.1,
            "Year gain USD-adj (%)": 0.75,
            "tradetime": "07-12-24 00:00",
            "name": "China A50"
        },
        {
            "21EMA*": 2.22,
            "50EMA*": 4.69,
            "200EMA*": 12.17,
            "PctBelow52wkHi": 0.0,
            "PctAbove52wkLo": 31.27,
            "Year gain (%)": 12.75,
            "FxGain": -0.39,
            "Year gain USD-adj (%)": 12.31,
            "tradetime": "07-12-24 00:00",
            "name": "India Nifty 50"
        },
        {
            "21EMA*": 1.3,
            "50EMA*": 1.22,
            "200EMA*": 5.06,
            "PctBelow52wkHi": 1.67,
            "PctAbove52wkLo": 20.58,
            "Year gain (%)": 9.75,
            "FxGain": -1.18,
            "Year gain USD-adj (%)": 8.46,
            "tradetime": "07-12-24 00:00",
            "name": "EURONEXT 100"
        },
        {
            "21EMA*": 1.48,
            "50EMA*": 1.68,
            "200EMA*": 7.5,
            "PctBelow52wkHi": 1.69,
            "PctAbove52wkLo": 26.15,
            "Year gain (%)": 11.37,
            "FxGain": -1.18,
            "Year gain USD-adj (%)": 10.06,
            "tradetime": "07-12-24 00:00",
            "name": "Spain IBEX 35"
        },
        {
            "21EMA*": 2.29,
            "50EMA*": 3.42,
            "200EMA*": 7.26,
            "PctBelow52wkHi": 0.0,
            "PctAbove52wkLo": 19.77,
            "Year gain (%)": 11.02,
            "FxGain": -5.92,
            "Year gain USD-adj (%)": 4.45,
            "tradetime": "07-12-24 00:00",
            "name": "Swiss Market index"
        },
        {
            "21EMA*": 5.09,
            "50EMA*": 5.25,
            "200EMA*": 8.37,
            "PctBelow52wkHi": -1.09,
            "PctAbove52wkLo": 31.24,
            "Year gain (%)": 5.98,
            "FxGain": 0.0,
            "Year gain USD-adj (%)": 5.98,
            "tradetime": "07-12-24 00:00",
            "name": "Russell 2000 small-cap"
        },
        {
            "21EMA*": 2.19,
            "50EMA*": 2.39,
            "200EMA*": 7.85,
            "PctBelow52wkHi": 0.41,
            "PctAbove52wkLo": 28.34,
            "Year gain (%)": 9.79,
            "FxGain": -4.2,
            "Year gain USD-adj (%)": 5.18,
            "tradetime": "07-12-24 00:00",
            "name": "Sweden OMX 30"
        },
        {
            "21EMA*": 2.41,
            "50EMA*": 4.29,
            "200EMA*": 11.72,
            "PctBelow52wkHi": -0.13,
            "PctAbove52wkLo": 35.65,
            "Year gain (%)": 16.06,
            "FxGain": 0.0,
            "Year gain USD-adj (%)": 16.06,
            "tradetime": "07-12-24 00:00",
            "name": "Russell 3000 (overall U.S market)"
        },
        {
            "21EMA*": 3.69,
            "50EMA*": 3.61,
            "200EMA*": 4.39,
            "PctBelow52wkHi": 3.95,
            "PctAbove52wkLo": 14.54,
            "Year gain (%)": -3.94,
            "FxGain": -10.63,
            "Year gain USD-adj (%)": -14.15,
            "tradetime": "07-12-24 00:00",
            "name": "Brazil Ibovespa "
        },
        {
            "21EMA*": 3.17,
            "50EMA*": 1.54,
            "200EMA*": 0.46,
            "PctBelow52wkHi": 6.4,
            "PctAbove52wkLo": 14.02,
            "Year gain (%)": -4.24,
            "FxGain": -3.64,
            "Year gain USD-adj (%)": -7.73,
            "tradetime": "07-12-24 00:00",
            "name": "Mexico IPC "
        },
        {
            "21EMA*": 2.81,
            "50EMA*": 4.04,
            "200EMA*": 8.41,
            "PctBelow52wkHi": -0.0,
            "PctAbove52wkLo": 28.84,
            "Year gain (%)": 10.87,
            "FxGain": 0.1,
            "Year gain USD-adj (%)": 10.99,
            "tradetime": "07-11-24 00:00",
            "name": "Israel TA-35 "
        },
        {
            "21EMA*": 2.47,
            "50EMA*": 2.73,
            "200EMA*": 3.45,
            "PctBelow52wkHi": -0.0,
            "PctAbove52wkLo": 12.97,
            "Year gain (%)": 3.1,
            "FxGain": -3.16,
            "Year gain USD-adj (%)": -0.17,
            "tradetime": "07-12-24 00:00",
            "name": "New Zealand NZX 50"
        },
        {
            "21EMA*": 2.89,
            "50EMA*": 7.2,
            "200EMA*": 21.21,
            "PctBelow52wkHi": 1.94,
            "PctAbove52wkLo": 49.47,
            "Year gain (%)": 33.38,
            "FxGain": -5.53,
            "Year gain USD-adj (%)": 26.0,
            "tradetime": "07-12-24 00:00",
            "name": "Taiwan TSEC weighted"
        },
        {
            "21EMA*": 2.69,
            "50EMA*": 3.09,
            "200EMA*": 3.39,
            "PctBelow52wkHi": 1.42,
            "PctAbove52wkLo": 10.69,
            "Year gain (%)": 0.75,
            "FxGain": -4.59,
            "Year gain USD-adj (%)": -3.87,
            "tradetime": "07-12-24 00:00",
            "name": "Indonesia Jakarta composite"
        },
        {
            "21EMA*": -1.19,
            "50EMA*": -4.0,
            "200EMA*": -10.31,
            "PctBelow52wkHi": 25.88,
            "PctAbove52wkLo": 8.6,
            "Year gain (%)": -10.98,
            "FxGain": -2.1,
            "Year gain USD-adj (%)": -12.85,
            "tradetime": "07-12-24 00:00",
            "name": "China ChiNext"
        },
        {
            "21EMA*": 3.1,
            "50EMA*": 5.94,
            "200EMA*": 22.19,
            "PctBelow52wkHi": 0.37,
            "PctAbove52wkLo": 83.62,
            "Year gain (%)": 47.58,
            "FxGain": -10.47,
            "Year gain USD-adj (%)": 32.12,
            "tradetime": "07-11-24 00:00",
            "name": "Turkey Borsa Istanbul 100"
        },
        {
            "21EMA*": 1.26,
            "50EMA*": 1.9,
            "200EMA*": 6.61,
            "PctBelow52wkHi": 1.83,
            "PctAbove52wkLo": 22.7,
            "Year gain (%)": 7.9,
            "FxGain": -1.18,
            "Year gain USD-adj (%)": 6.63,
            "tradetime": "07-12-24 00:00",
            "name": "Austrian ATX"
        },
        {
            "21EMA*": 1.9,
            "50EMA*": 2.39,
            "200EMA*": 5.95,
            "PctBelow52wkHi": 6.21,
            "PctAbove52wkLo": 30.6,
            "Year gain (%)": 13.25,
            "FxGain": 0.02,
            "Year gain USD-adj (%)": 13.27,
            "tradetime": "07-12-24 00:00",
            "name": "Hang Seng China Enterprise"
        },
        {
            "21EMA*": 1.65,
            "50EMA*": 3.09,
            "200EMA*": 10.79,
            "PctBelow52wkHi": 0.0,
            "PctAbove52wkLo": 32.33,
            "Year gain (%)": 20.09,
            "FxGain": -2.1,
            "Year gain USD-adj (%)": 17.57,
            "tradetime": "07-12-24 00:00",
            "name": "Netherlands AEX "
        },
        {
            "21EMA*": 2.32,
            "50EMA*": 3.07,
            "200EMA*": 6.5,
            "PctBelow52wkHi": 0.0,
            "PctAbove52wkLo": 22.77,
            "Year gain (%)": 8.96,
            "FxGain": 0.02,
            "Year gain USD-adj (%)": 8.98,
            "tradetime": "07-12-24 00:00",
            "name": "Belgium BEL20"
        }
    ]
}